pyc3dtools/__init__.py
pyc3dtools/pyc3dtools.py
pyc3dtools-0.3.2.dist-info/LICENSE
pyc3dtools-0.3.2.dist-info/METADATA
pyc3dtools-0.3.2.dist-info/WHEEL
pyc3dtools-0.3.2.dist-info/top_level.txt
pyc3dtools-0.3.2.dist-info/RECORD
