Metadata-Version: 2.1
Name: pyc3dtools
Version: 0.3.2
Summary: C3Dtools API package - Read c3d files
Home-page: https://github.com/etoshey/pyc3dtools
Author: Soroosh.b.k (C3Dtools.com)
Author-email: <soroosh.b.k@gmail.com>
License: MIT
Keywords: python,c3d,motion capture,biomechanics
Classifier: Development Status :: 1 - Planning
Classifier: Intended Audience :: Developers
Classifier: Programming Language :: Python :: 3
Classifier: Operating System :: Unix
Classifier: Operating System :: MacOS :: MacOS X
Classifier: Operating System :: Microsoft :: Windows
License-File: LICENSE
Requires-Dist: numpy
Requires-Dist: tqdm
Requires-Dist: requests
